mots_vides-2015.5.11.dist-info/metadata.json
mots_vides-2015.5.11.dist-info/top_level.txt
mots_vides-2015.5.11.dist-info/entry_points.txt
mots_vides-2015.5.11.dist-info/DESCRIPTION.rst
mots_vides-2015.5.11.dist-info/RECORD
mots_vides-2015.5.11.dist-info/METADATA
mots_vides-2015.5.11.dist-info/WHEEL
mots_vides/factory.py
mots_vides/constants.py
mots_vides/exceptions.py
mots_vides/stop_words.py
mots_vides/__init__.py
mots_vides/scripts/rebaser.py
mots_vides/scripts/merger.py
mots_vides/scripts/__init__.py
mots_vides/tests/factory.py
mots_vides/tests/shortcut.py
mots_vides/tests/stop_words.py
mots_vides/tests/__init__.py
mots_vides/datas/turkish.txt
mots_vides/datas/english.txt
mots_vides/datas/hungarian.txt
mots_vides/datas/hindi.txt
mots_vides/datas/chinese.txt
mots_vides/datas/czech.txt
mots_vides/datas/armenian.txt
mots_vides/datas/dutch.txt
mots_vides/datas/japanese.txt
mots_vides/datas/polish.txt
mots_vides/datas/bulgarian.txt
mots_vides/datas/ukrainian.txt
mots_vides/datas/norwegian.txt
mots_vides/datas/lithuanian.txt
mots_vides/datas/catalan.txt
mots_vides/datas/greek.txt
mots_vides/datas/urdu.txt
mots_vides/datas/slovak.txt
mots_vides/datas/latvian.txt
mots_vides/datas/marathi.txt
mots_vides/datas/russian.txt
mots_vides/datas/arabic.txt
mots_vides/datas/german.txt
mots_vides/datas/thai.txt
mots_vides/datas/irish.txt
mots_vides/datas/persian.txt
mots_vides/datas/korean.txt
mots_vides/datas/romanian.txt
mots_vides/datas/swedish.txt
mots_vides/datas/basque.txt
mots_vides/datas/italian.txt
mots_vides/datas/spanish.txt
mots_vides/datas/indonesian.txt
mots_vides/datas/portuguese.txt
mots_vides/datas/danish.txt
mots_vides/datas/french.txt
mots_vides/datas/finnish.txt
mots_vides/datas/galician.txt
mots_vides/datas/bengali.txt
