Metadata-Version: 1.1
Name: mots-vides
Version: 2015.5.11
Summary: Python library for managing stop words in many languages.
Home-page: https://github.com/Fantomas42/mots-vides
Author: Fantomas42
Author-email: fantomas42@gmail.com
License: Copyright (c) 2015, Julien Fache
